csv2pdf.py
csv2pdf-0.1.4.dist-info/LICENSE
csv2pdf-0.1.4.dist-info/METADATA
csv2pdf-0.1.4.dist-info/WHEEL
csv2pdf-0.1.4.dist-info/top_level.txt
csv2pdf-0.1.4.dist-info/RECORD
