Metadata-Version: 2.1
Name: csv2pdf
Version: 0.1.4
Summary: Easily convert CSV Files to PDF Files using Python!
Home-page: https://github.com/TECH-SAVVY-GUY/csv2pdf
Author: SOHAM DATTA
Author-email: dattasoham805@gmail.com
License: UNKNOWN
Keywords: csv,pdf,csv2pdf,converter,file-converter
Platform: UNKNOWN
Classifier: Programming Language :: Python :: 3
Classifier: License :: OSI Approved :: MIT License
Classifier: Operating System :: OS Independent
Requires-Python: >=3.6
License-File: LICENSE
